respredai/__init__.py
respredai/cli.py
respredai/core/__init__.py
respredai/core/metrics.py
respredai/core/models.py
respredai/core/params.py
respredai/core/pipe.py
respredai/core/pipeline.py
respredai/io/__init__.py
respredai/io/config.py
respredai/io/reproducibility.py
respredai/visualization/__init__.py
respredai/visualization/confusion_matrix.py
respredai/visualization/feature_importance.py
respredai/visualization/html_report.py
respredai-1.5.1.dist-info/licenses/LICENSE
respredai-1.5.1.dist-info/METADATA
respredai-1.5.1.dist-info/WHEEL
respredai-1.5.1.dist-info/entry_points.txt
respredai-1.5.1.dist-info/top_level.txt
respredai-1.5.1.dist-info/RECORD
