Metadata-Version: 2.4
Name: ResPredAI
Version: 1.5.1
Summary: Antimicrobial Resistance predictions via AI models
Author-email: Ettore Rocchi <ettore.rocchi3@unibo.it>
Maintainer-email: Ettore Rocchi <ettore.rocchi3@unibo.it>
License: MIT
Project-URL: Homepage, https://github.com/EttoreRocchi/ResPredAI
Project-URL: Bug Reports, https://github.com/EttoreRocchi/ResPredAI/issues
Project-URL: Source, https://github.com/EttoreRocchi/ResPredAI
Project-URL: Documentation, https://ettorerocchi.github.io/ResPredAI/
Keywords: machine-learning,antimicrobial-resistance
Classifier: Development Status :: 4 - Beta
Classifier: Intended Audience :: Science/Research
Classifier: License :: OSI Approved :: MIT License
Classifier: Programming Language :: Python :: 3
Classifier: Programming Language :: Python :: 3.9
Classifier: Programming Language :: Python :: 3.10
Classifier: Programming Language :: Python :: 3.11
Classifier: Programming Language :: Python :: 3.12
Classifier: Topic :: Scientific/Engineering :: Artificial Intelligence
Requires-Python: >=3.9
License-File: LICENSE
Requires-Dist: numpy<3.0.0,>=1.24.0
Requires-Dist: pandas<3.0.0,>=2.0.0
Requires-Dist: matplotlib<4.0.0,>=3.7.0
Requires-Dist: seaborn<1.0.0,>=0.12.0
Requires-Dist: scikit-learn<2.0.0,>=1.5.0
Requires-Dist: xgboost<3.0.0,>=2.0.0
Requires-Dist: catboost<2.0.0,>=1.2.0
Requires-Dist: tabpfn>=6.0.0
Requires-Dist: typer<1.0.0,>=0.9.0
Requires-Dist: rich<14.0.0,>=13.0.0
Requires-Dist: tqdm<5.0.0,>=4.65.0
Requires-Dist: shap<1.0.0,>=0.45.0
Provides-Extra: dev
Requires-Dist: pytest>=8.0.0; extra == "dev"
Requires-Dist: ruff>=0.14.0; extra == "dev"
Requires-Dist: pre-commit>=3.0.0; extra == "dev"
Provides-Extra: docs
Requires-Dist: sphinx>=7.0.0; extra == "docs"
Requires-Dist: pydata-sphinx-theme>=0.15.0; extra == "docs"
Requires-Dist: myst-parser>=3.0.0; extra == "docs"
Dynamic: license-file
